webscrap_tool/__init__.py
webscrap_tool/frontend/build/asset-manifest.json
webscrap_tool/frontend/build/bootstrap.min.css
webscrap_tool/frontend/build/index.html
webscrap_tool/frontend/build/static/css/471.9fca079c.chunk.css
webscrap_tool/frontend/build/static/css/471.9fca079c.chunk.css.map
webscrap_tool/frontend/build/static/css/main.6d6ce492.chunk.css
webscrap_tool/frontend/build/static/css/main.6d6ce492.chunk.css.map
webscrap_tool/frontend/build/static/js/0.373c7195.chunk.js
webscrap_tool/frontend/build/static/js/0.373c7195.chunk.js.map
webscrap_tool/frontend/build/static/js/1.28af7217.chunk.js
webscrap_tool/frontend/build/static/js/1.28af7217.chunk.js.map
webscrap_tool/frontend/build/static/js/10.95523ce2.chunk.js
webscrap_tool/frontend/build/static/js/10.95523ce2.chunk.js.map
webscrap_tool/frontend/build/static/js/100.807817ed.chunk.js
webscrap_tool/frontend/build/static/js/100.807817ed.chunk.js.map
webscrap_tool/frontend/build/static/js/101.c90799ba.chunk.js
webscrap_tool/frontend/build/static/js/101.c90799ba.chunk.js.map
webscrap_tool/frontend/build/static/js/102.7381c059.chunk.js
webscrap_tool/frontend/build/static/js/102.7381c059.chunk.js.map
webscrap_tool/frontend/build/static/js/103.86b1d765.chunk.js
webscrap_tool/frontend/build/static/js/103.86b1d765.chunk.js.map
webscrap_tool/frontend/build/static/js/104.4b0c69b7.chunk.js
webscrap_tool/frontend/build/static/js/104.4b0c69b7.chunk.js.map
webscrap_tool/frontend/build/static/js/105.95bf39ee.chunk.js
webscrap_tool/frontend/build/static/js/105.95bf39ee.chunk.js.map
webscrap_tool/frontend/build/static/js/106.0c7c48d8.chunk.js
webscrap_tool/frontend/build/static/js/106.0c7c48d8.chunk.js.map
webscrap_tool/frontend/build/static/js/107.4b7572c4.chunk.js
webscrap_tool/frontend/build/static/js/107.4b7572c4.chunk.js.map
webscrap_tool/frontend/build/static/js/108.873964a8.chunk.js
webscrap_tool/frontend/build/static/js/108.873964a8.chunk.js.map
webscrap_tool/frontend/build/static/js/109.5e48163c.chunk.js
streamlit_webscrap_tool-0.0.1.dist-info/LICENSE
streamlit_webscrap_tool-0.0.1.dist-info/METADATA
streamlit_webscrap_tool-0.0.1.dist-info/WHEEL
streamlit_webscrap_tool-0.0.1.dist-info/top_level.txt
streamlit_webscrap_tool-0.0.1.dist-info/RECORD
